<?xml version="1.0" encoding="UTF-8"?>
<Properties>
  <_id>
    <oid>547d3781bd354316580081c9</oid>
  </_id>
  <archive_url>https://api.github.com/repos/di/repyt/{archive_format}{/ref}</archive_url>
  <assignees_url>https://api.github.com/repos/di/repyt/assignees{/user}</assignees_url>
  <blobs_url>https://api.github.com/repos/di/repyt/git/blobs{/sha}</blobs_url>
  <branches_url>https://api.github.com/repos/di/repyt/branches{/branch}</branches_url>
  <clone_url>https://github.com/di/repyt.git</clone_url>
  <collaborators_url>https://api.github.com/repos/di/repyt/collaborators{/collaborator}</collaborators_url>
  <comments_url>https://api.github.com/repos/di/repyt/comments{/number}</comments_url>
  <commits_url>https://api.github.com/repos/di/repyt/commits{/sha}</commits_url>
  <compare_url>https://api.github.com/repos/di/repyt/compare/{base}...{head}</compare_url>
  <contents_url>https://api.github.com/repos/di/repyt/contents/{+path}</contents_url>
  <contributors_url>https://api.github.com/repos/di/repyt/contributors</contributors_url>
  <created_at>12/2/2014 3:24:26 AM</created_at>
  <default_branch>master</default_branch>
  <description>Automatically re-run Python commands when files change.</description>
  <downloads_url>https://api.github.com/repos/di/repyt/downloads</downloads_url>
  <events_url>https://api.github.com/repos/di/repyt/events</events_url>
  <fork>False</fork>
  <forks>0</forks>
  <forks_count>0</forks_count>
  <forks_url>https://api.github.com/repos/di/repyt/forks</forks_url>
  <full_name>di/repyt</full_name>
  <git_commits_url>https://api.github.com/repos/di/repyt/git/commits{/sha}</git_commits_url>
  <git_refs_url>https://api.github.com/repos/di/repyt/git/refs{/sha}</git_refs_url>
  <git_tags_url>https://api.github.com/repos/di/repyt/git/tags{/sha}</git_tags_url>
  <git_url>git://github.com/di/repyt.git</git_url>
  <has_downloads>True</has_downloads>
  <has_issues>True</has_issues>
  <has_pages>False</has_pages>
  <has_wiki>True</has_wiki>
  <homepage>https://pypi.python.org/pypi/repyt</homepage>
  <hooks_url>https://api.github.com/repos/di/repyt/hooks</hooks_url>
  <html_url>https://github.com/di/repyt</html_url>
  <id>27413082</id>
  <issue_comment_url>https://api.github.com/repos/di/repyt/issues/comments/{number}</issue_comment_url>
  <issue_events_url>https://api.github.com/repos/di/repyt/issues/events{/number}</issue_events_url>
  <issues_url>https://api.github.com/repos/di/repyt/issues{/number}</issues_url>
  <keys_url>https://api.github.com/repos/di/repyt/keys{/key_id}</keys_url>
  <labels_url>https://api.github.com/repos/di/repyt/labels{/name}</labels_url>
  <language>Python</language>
  <languages_url>https://api.github.com/repos/di/repyt/languages</languages_url>
  <merges_url>https://api.github.com/repos/di/repyt/merges</merges_url>
  <milestones_url>https://api.github.com/repos/di/repyt/milestones{/number}</milestones_url>
  <mirror_url>
  </mirror_url>
  <name>repyt</name>
  <network_count>0</network_count>
  <notifications_url>https://api.github.com/repos/di/repyt/notifications{?since,all,participating}</notifications_url>
  <open_issues>0</open_issues>
  <open_issues_count>0</open_issues_count>
  <owner>
    <avatar_url>https://avatars.githubusercontent.com/u/294415?v=3</avatar_url>
    <events_url>https://api.github.com/users/di/events{/privacy}</events_url>
    <followers_url>https://api.github.com/users/di/followers</followers_url>
    <following_url>https://api.github.com/users/di/following{/other_user}</following_url>
    <gists_url>https://api.github.com/users/di/gists{/gist_id}</gists_url>
    <gravatar_id>
    </gravatar_id>
    <html_url>https://github.com/di</html_url>
    <id>294415</id>
    <login>di</login>
    <organizations_url>https://api.github.com/users/di/orgs</organizations_url>
    <received_events_url>https://api.github.com/users/di/received_events</received_events_url>
    <repos_url>https://api.github.com/users/di/repos</repos_url>
    <site_admin>False</site_admin>
    <starred_url>https://api.github.com/users/di/starred{/owner}{/repo}</starred_url>
    <subscriptions_url>https://api.github.com/users/di/subscriptions</subscriptions_url>
    <type>User</type>
    <url>https://api.github.com/users/di</url>
  </owner>
  <permissions>
    <admin>False</admin>
    <pull>True</pull>
    <push>False</push>
  </permissions>
  <private>False</private>
  <pulls_url>https://api.github.com/repos/di/repyt/pulls{/number}</pulls_url>
  <pushed_at>12/2/2014 3:25:56 AM</pushed_at>
  <releases_url>https://api.github.com/repos/di/repyt/releases{/id}</releases_url>
  <size>0</size>
  <ssh_url>git@github.com:di/repyt.git</ssh_url>
  <stargazers_count>1</stargazers_count>
  <stargazers_url>https://api.github.com/repos/di/repyt/stargazers</stargazers_url>
  <statuses_url>https://api.github.com/repos/di/repyt/statuses/{sha}</statuses_url>
  <subscribers_count>1</subscribers_count>
  <subscribers_url>https://api.github.com/repos/di/repyt/subscribers</subscribers_url>
  <subscription_url>https://api.github.com/repos/di/repyt/subscription</subscription_url>
  <svn_url>https://github.com/di/repyt</svn_url>
  <tags_url>https://api.github.com/repos/di/repyt/tags</tags_url>
  <teams_url>https://api.github.com/repos/di/repyt/teams</teams_url>
  <trees_url>https://api.github.com/repos/di/repyt/git/trees{/sha}</trees_url>
  <updated_at>12/2/2014 3:26:22 AM</updated_at>
  <url>https://api.github.com/repos/di/repyt</url>
  <watchers>1</watchers>
  <watchers_count>1</watchers_count>
</Properties>